secureai/__init__.py
secureai/httpx/__init__.py
secureai/httpx/async_client.py
secureai/httpx/sync_client.py
secureai/openai.py
secureai/ratls.py
secureai/ssl_context.py
secureai/utils.py
secureai/verifiers/__init__.py
secureai/verifiers/base.py
secureai/verifiers/collateral.json
secureai/verifiers/errors.py
secureai/verifiers/tdx.py
secureai-0.2.0.dist-info/WHEEL
secureai-0.2.0.dist-info/METADATA
secureai-0.2.0.dist-info/RECORD
