Metadata-Version: 2.3
Name: secureai
Version: 0.2.0
Summary: Add your description here
Requires-Dist: dcap-qvl>=0.3.2
Requires-Dist: dstack-sdk>=0.5.3
Requires-Dist: httpx>=0.28.1
Requires-Dist: openai>=2.7.2
Requires-Python: >=3.10
